{"trung_nien_nu_0.jpg": "Set b\u1ed9 - S1754 - Th\u01b0\u01a1ng hi\u1ec7u Zonbig", "trung_nien_nu_1.jpg": "Set b\u1ed9 - S1709 - Th\u01b0\u01a1ng hi\u1ec7u Zonbig", "trung_nien_nu_2.jpg": "\u0110\u1ed3 b\u1ed9 trung ni\u00ean cho b\u00e0 cho m\u1eb9, ch\u1ea5t li\u1ec7u m\u00e1t, th\u1ea5m h\u00fat m\u1ed3 h\u00f4i, \u0111\u1ed3 b\u1ed9 n\u1eef ki\u1ec3u set \u0111i ch\u01a1i , b\u1ed9 \u0111\u1ed3 trung ni\u00ean TN01", "trung_nien_nu_3.jpg": "\u0110\u1ed3 b\u1ed9 trung ni\u00ean cho b\u00e0 cho m\u1eb9, ch\u1ea5t li\u1ec7u L\u1ee5a H\u00e0n m\u00e1t, th\u1ea5m h\u00fat m\u1ed3 h\u00f4i, \u0111\u1ed3 b\u1ed9 n\u1eef ki\u1ec3u set \u0111i ch\u01a1i , b\u1ed9 \u0111\u1ed3 trung ni\u00ean, Nesa Shop", "trung_nien_nu_4.jpg": "V\u00e1y trung ni\u00ean cho m\u1eb9 ch\u1ea5t li\u1ec7u l\u1ee5a Mango cao c\u1ea5p si\u00eau m\u1ec1m m\u00e1t kh\u00f4ng nh\u0103n x\u00f9 h\u1ecda ti\u1ebft hoa ch\u00e2n c\u1ef1c \u0111\u1eb9p - Tu\u1ea5n T\u00fa Store 68", "trung_nien_nu_5.jpg": "Set \u0111\u1ed3 trung ni\u00ean B\u1ed9 ph\u1ed1i \u00c1o l\u1ee5a Satin m\u1ec1m m\u01b0\u1ee3t h\u1ecda ti\u1ebft nh\u00e3 nh\u1eb7n v\u00e0 qu\u1ea7n \u0111\u0169i \u0111en d\u00e0y d\u1eb7n size t\u1eeb 45kg t\u1edbi 65kg - Tu\u1ea5n T\u00fa Store 68", "trung_nien_nu_6.jpg": "\u0110\u1ed3 trung ni\u00ean B\u1ed9 ph\u1ed1i \u00c1o l\u1ee5a H\u00e0n Ch\u00e2u m\u1ec1m m\u01b0\u1ee3t tho\u00e1ng m\u00e1t v\u1edbi qu\u1ea7n \u0110\u0169i v\u1ea3i d\u00e0y d\u1eb7n \u0111\u1ee7 size t\u1eeb 45kg t\u1edbi 65kg - Tu\u1ea5n T\u00fa Store 68", "trung_nien_nu_7.jpg": "\u0110\u1ed3 B\u1ed9 \u0110\u0169i Trung Ni\u00ean Ch\u1ea5t Li\u1ec7u \u0110\u0169i Cao C\u1ea5p Cho M\u1eb9 V\u00e0 B\u00e0 M\u1eb7c \u0110i Ti\u1ec7c \u0110i Ch\u01a1i - Tu\u1ea5n T\u00fa Store 68", "trung_nien_nu_8.jpg": "B\u1ed9 Trung Ni\u00ean Ph\u1ed1i \u00c1o Voan 2 L\u1edbp V\u00e0 Qu\u1ea7n \u0110\u0169i \u0110en Ch\u1ea5t Li\u1ec7u M\u00e1t M\u1ebb S\u00e0nh \u0110i\u1ec7u C\u00e1 T\u00ednh Cho B\u00e0 V\u00e0 M\u1eb9 - Tu\u1ea5n T\u00fa Store 68", "trung_nien_nu_9.jpg": "SET \u0110\u1ed2 B\u1ed8 TRUNG NI\u00caN CHO M\u1eb8 V\u00c0 B\u00c0 SANG TR\u1eccNG", "trung_nien_nu_10.jpg": "\u0110\u1ea7m Cho M\u1eb9 Trung Ni\u00ean Ch\u1ea5t Li\u1ec7u L\u1ee5a Mango Cao C\u1ea5p M\u1ec1m M\u1ecbn Kh\u00f4ng Nh\u0103n X\u00f9 M\u1eabu M\u00e3 \u0110a D\u1ea1ng \u0110\u1ee7 Size T\u1eeb 45-65kg - Tu\u1ea5n T\u00fa Store 68", "trung_nien_nu_11.jpg": "\u00c1o th\u00eau hoa trung ni\u00ean d\u00e1ng d\u00e0i", "trung_nien_nu_12.jpg": "B\u1ed9 Lanh Trung Ni\u00ean Cao C\u1ea5p \u0110\u00e3 Qua X\u1eed L\u00fd Co \u0110\u1ee7 Size T\u1eeb 47 T\u1edbi 70kg - Tu\u1ea5n T\u00fa Store 68", "trung_nien_nu_13.jpg": "V\u00e1y Trung Ni\u00ean Sang Tr\u1ecdng Ch\u1ea5t Li\u1ec7u L\u1ee5a Mango M\u1ec1m M\u01b0\u1ee3t V\u00e0 Tho\u00e1ng M\u00e1t 2023 - Tu\u1ea5n T\u00fa Store 68", "trung_nien_nu_14.jpg": "\u00c1o Ki\u1ec3u Cho M\u1eb9 Ch\u1ea5t Li\u1ec7u \u0110\u0169i Cao C\u1ea5p Th\u00eau Hoa Tinh X\u1ea3o Ph\u00f9 H\u1ee3p V\u1edbi Ph\u1ee5 N\u1eef T\u1eeb 55-70 Tu\u1ed5i - Tu\u1ea5n T\u00fa Store 68", "trung_nien_nu_15.jpg": "\u0110\u1ed3 b\u1ed9 m\u1eb7c nh\u00e0 trung ni\u00ean n\u1eef, b\u1ed9 \u0111\u1ed3 \u00e1o ng\u1eafn tay qu\u1ea7n l\u1eedng ch\u1ea5t li\u1ec7u \u0111\u0169i lanh cao c\u1ea5p m\u1ec1n m\u1ea1i tho\u00e1ng m\u00e1t cho b\u00e0 cho m\u1eb9", "trung_nien_nu_16.jpg": "\u0110\u1ea7m x\u00f2e thi\u1ebft k\u1ebf trung ni\u00ean cao c\u1ea5p sang tr\u1ecdng C\u1ed5 tim c\u1ed9t n\u01a1 tay d\u00e0i m\u00e0u T\u00edm hu\u1ebf TTV STORE TTV1126", "trung_nien_nu_17.jpg": "SET \u0110\u1ed2 B\u1ed8 TRUNG NI\u00caN CHO M\u1eb8 V\u00c0 B\u00c0 SANG TR\u1eccNG", "trung_nien_nu_18.jpg": "\u0110\u1ed3 B\u1ed9 M\u1eb7c Nh\u00e0 Trung Ni\u00ean Ch\u1ea5t Li\u1ec7u Lanh Cao C\u1ea5p \u0110\u00e3 Qua X\u1eed L\u00fd Co Size t\u1eeb 47-70kg 2023 - Tu\u1ea5n T\u00fa Store", "trung_nien_nu_19.jpg": "Qu\u1ea7n \u00c1o Trung Ni\u00ean Cho M\u1eb9 B\u1ed9 L\u1ee5a Satin Tay L\u1ee1 Ki\u1ec3u D\u00e1ng Sang Tr\u1ecdng Ph\u00f9 H\u1ee3p V\u1edbi \u0110\u1ed9 Tu\u1ed5i T\u1eeb 50 t\u1edbi 70 - Tu\u1ea5n T\u00fa Store", "trung_nien_nu_20.jpg": "\u0110\u1ed3 B\u1ed9 Trung Ni\u00ean N\u1eef - B\u1ed9 \u0110\u0169i Tay L\u1ee1 - Kh\u00f4ng Nh\u0103n Kh\u00f4ng X\u00f9 - \u0110\u1ee7 Size t\u1eeb 46kg-70kg - Tu\u1ea5n T\u00fa Store", "trung_nien_nu_21.jpg": "\u00c1o ki\u1ec3u n\u1eef hoa nh\u00ed c\u1ed5 V, ng\u1eafn tay, ch\u1ea5t \u0111\u0169i m\u1ec1m m\u1ecfng, th\u1eddi trang trung ni\u00ean n\u1eef \u0110\u0169i Vi\u1ec7t DVALE30", "trung_nien_nu_22.jpg": "A\u00f3 \u0111\u0169i n\u1eef tay l\u1ee1 k\u00edn \u0111\u00e1o 3 m\u00e0u thanh l\u1ecbch full size 40-65kg Th\u1eddi trang trung ni\u00ean n\u1eef Haint Boutique ALE19", "trung_nien_nu_23.jpg": "\u00c1o \u0110\u0169i N\u1eef, \u00c1o Ki\u1ec3u Trung Ni\u00ean Cho M\u1eb9 M\u1eb7c Nh\u00e0 M\u00f9a H\u00e8 Ch\u1ea5t V\u1ea3i Tho\u00e1ng M\u00e1t M\u1ec1m Nh\u1eb9 ARCTIC HUNTER AH19", "trung_nien_nu_24.jpg": "\u00c1o \u0110\u0169i N\u1eef D\u00e1ng R\u1ed9ng Phong C\u00e1ch Thanh L\u1ecbch Cho Ph\u1ee5 N\u1eef Tu\u1ed5i Trung Ni\u00ean \u0110\u0169i Vi\u1ec7t DVALE19", "trung_nien_nu_25.jpg": "\u0110\u1ea7m linen d\u00e1ng su\u00f4ng - \u0110\u1ea7m su\u00f4ng trung ni\u00ean ARCTIC HUNTER ch\u1ea5t \u0111\u0169i m\u1ec1m m\u00e1t AH84", "trung_nien_nu_26.jpg": "\u00c1o trung ni\u00ean form r\u1ed9ng fullsize M \u0111\u1ebfn 2XL, \u00e1o \u0111\u0169i n\u1eef th\u00eau hoa h\u1ecda ti\u1ebft d\u1ec5 mix \u0111\u1ed3 m\u1eabu m\u1edbi \u0110\u0169i Vi\u1ec7t ALE17", "trung_nien_nu_27.jpg": "\u00c1o trung ni\u00ean n\u1eef c\u1ed9c tay in hoa, \u00c1o \u0111\u1ee7 size ch\u1ea5t v\u1ea3i m\u00e1t m\u1ecbn \u0110\u0169i Vi\u1ec7t A18", "trung_nien_nu_28.jpg": "[M\u1eabu M\u1edbi 2022] V\u00e1y \u0110\u1ea7m Trung Ni\u00ean Trung Ni\u00ean H\u1ecda Ti\u1ebft C\u1ef1c \u0110\u1eb9p  - D\u00e0nh Cho C\u00e1c Qu\u00fd B\u00e0 2021 - Tu\u1ea5n T\u00fa Store", "trung_nien_nu_29.jpg": "(X\u1ea2 KHO) \u00c1O LEN M\u1eceNG M\u1eb6C M\u00d9A THU CHO NG\u01af\u1edcI TRUNG NI\u00caN", "trung_nien_nu_30.jpg": "\u00c1o Ki\u1ec3u Trung Ni\u00ean Tay L\u1ee1 - Ch\u1ea5t Li\u1ec7u L\u1ee5a Satin Cao C\u1ea5p D\u00e0nh Cho Ng\u01b0\u1eddi Trung Tu\u1ed5i - Tu\u1ea5n T\u00fa Store", "trung_nien_nu_31.jpg": "B\u1ed9 \u0110\u1ed3 Trung Ni\u00ean - B\u1ed9 Ph\u1ed1i \u00c1o L\u1ee5a Satin v\u00e0 Qu\u1ea7n \u0110\u0169i Cao C\u1ea5p - D\u00e0nh Cho Ph\u1ee5 N\u1eef Vi\u1ec7t Nam 2021 - Tu\u1ea5n T\u00fa Store", "trung_nien_nu_32.jpg": "\u0110\u1ed3 b\u1ed9 n\u1eef - ch\u1ea5t li\u1ec7u Nhung tuy\u1ebft cao c\u1ea5p (N3)", "trung_nien_nu_33.jpg": "b\u1ed9 \u0111\u1ed3 m\u1eb7c nh\u00e0 trung ni\u00ean n\u1eef v\u1ea3i lanh m\u00e1t l\u1ecbm cho b\u00e0 cho m\u1eb9 m\u00f3n qu\u00e0 v\u00f4 c\u00f9ng \u00fd ngh\u0129a", "trung_nien_nu_34.jpg": "B\u1ed9 \u0111\u1ed3 m\u1eb7c nh\u00e0 trung ni\u00ean n\u1eef _ B\u1ed9 \u0111\u1ed3 thun l\u1ea1nh m\u1ec1m m\u1ecbn_B\u1ed9 \u0111\u1ed3 cho m\u1eb9 m\u1eabu m\u1edbi", "trung_nien_nu_35.jpg": "[M\u1eabu M\u1edbi] - B\u1ed9 Lanh cao c\u1ea5p ( \u0111\u00e3 qua x\u1eed l\u00fd co ) - \u0111\u1ee7 size t\u1eeb 47 - 70kg -  d\u00e0nh cho qu\u00fd b\u00e0 2021 - Tu\u1ea5n T\u00fa Store", "trung_nien_nu_36.jpg": "(Ri\u00eang \u00c1o) \u00c1o Ki\u1ec3u Trung Ni\u00ean  - L\u1ee5a H\u00e0n Ch\u00e2u Cao C\u1ea5p - M\u1ec1m M\u1ea1i - Tr\u1ebb Trung Cho C\u00e1c Qu\u00fd B\u00e0 - Tu\u1ea5n T\u00fa Store 68", "trung_nien_nu_37.jpg": "B\u1ed9 \u0110\u1ed3 Trung Ni\u00ean - B\u1ed9 \u0110\u0169i Cao C\u1ea5p - B\u1ed9 \u0110\u0169i H\u1ecda Ti\u1ebft Tr\u00f2n - D\u00e0nh Cho c\u00e1c Qu\u00fd B\u00e0 U40 - U50 - U60 - U70 - Laddy Store", "trung_nien_nu_38.jpg": "\u0110\u1ed3 b\u1ed9 trung ni\u00ean \u0111\u1eb9p - B\u1ed9 \u0111\u0169i trung ni\u00ean cao c\u1ea5p - ch\u1ea5t v\u1ea3i lo\u1ea1i 1 - Kh\u00f4ng nh\u0103n kh\u00f4ng x\u00f9 khi gi\u1eb7t - Laddy_store", "trung_nien_nu_39.jpg": "\u00c1o n\u1eef trung ni\u00ean cao c\u1ea5p ki\u1ec3u bigsize v\u1ea3i \u0111\u0169i m\u1eb7c r\u1ea5t m\u00e1t v\u00e0 tho\u1ea3i m\u00e1i freesize d\u00e0nh cho ng\u01b0\u1eddi t\u1eeb 55kg \u0111\u1ebfn 80kg \u0111\u1ed9 tu\u1ed5i t\u1eeb 40 \u0111\u1ebfn 65 tu\u1ed5i \u00e1o n\u1eef trung ni\u00ean \u00e1o cho m\u1eb9 \u00e1o cho b\u00e0 \u00e1o t\u1eb7ng m\u1eb9", "trung_nien_nu_40.jpg": "[BST M\u1edbi] B\u1ed9 \u0111\u0169i m\u1eb7c nh\u00e0 trung ni\u00ean \u00e1o tay l\u1ee1, qu\u1ea7n d\u00e0i  Vicci DTL02 v\u1ea3i \u0111\u0169i chun ph\u1ed1i h\u1ecda ti\u1ebft th\u00eau sang tr\u1ecdng", "trung_nien_nu_41.jpg": "Th\u1eddi trang trung ni\u00ean B\u1ed9 ph\u1ed1i \u00c1o \u0111\u0169i x\u01b0\u1edbc th\u00eau hoa tinh x\u1ea3o v\u00e0 qu\u1ea7n \u0111\u0169i l\u1ee5a m\u1ec1m m\u1ecbn \u0111\u1ee7 size t\u1eeb 45 t\u1edbi 65kg - Tu\u1ea5n T\u00fa Store 68", "trung_nien_nu_42.jpg": "\u0110o\u0302\u0300 Bo\u0323\u0302 Trung Nie\u0302n Cho Me\u0323 Sang Tro\u0323ng Ch\u1ea5t Li\u1ec7u L\u1ee5a Satin Cao C\u1ea5p M\u1ec1m M\u01b0\u1ee3t H\u1ecda Ti\u1ebft Tinh X\u1ea3o - Tu\u1ea5n T\u00fa Store 68", "trung_nien_nu_43.jpg": "\u0110\u1ed3 B\u1ed9 Trung Ni\u00ean Cho M\u1eb9 Ch\u1ea5t Li\u1ec7u L\u1ee5a H\u00e0n Ch\u00e2u Cao C\u1ea5p X\u1ecbn X\u00f2 - Tu\u1ea5n T\u00fa Store 68", "trung_nien_nu_44.jpg": "\u00c1o Trung Ni\u00ean Cho M\u1eb9 Ch\u1ea5t Li\u1ec7u \u0110\u0169i Cao C\u1ea5p Sang Tr\u1ecdng H\u1ecda Ti\u1ebft Th\u00eau Tinh X\u1ea3o - Tu\u1ea5n T\u00fa Store 68", "trung_nien_nu_45.jpg": "B\u1ed9 L\u1ee5a G\u1ea5m Cao C\u1ea5p Tay L\u1ee1 Cho M\u1eb9 Trung Ni\u00ean \u0110\u1ee7 Size T\u1eeb 45kg T\u1edbi 68kg - Tu\u1ea5n T\u00fa Store 68", "trung_nien_nu_46.jpg": "\u0110\u1ea7m su\u00f4ng thi\u1ebft k\u1ebf trung ni\u00ean cao c\u1ea5p sang tr\u1ecdng C\u1ed5 tr\u00f2n k\u1ebft hoa tay ng\u1eafn m\u00e0u T\u00edm hu\u1ebf TTV STORE TTV1339", "trung_nien_nu_47.jpg": "\u0110\u1ea7m x\u00f2e thi\u1ebft k\u1ebf trung ni\u00ean cao c\u1ea5p sang tr\u1ecdng C\u1ed5 tim tay ng\u1eafn m\u00e0u Xanh hoa TTV STORE TTV1326", "trung_nien_nu_48.jpg": "B\u1ed9 \u0110\u0169i Trung Ni\u00ean Hoa Th\u00eau C\u1ef1c \u0110\u1eb9p V\u1ea3i M\u00e1t \u0110\u01b0\u1eddng May Tinh X\u1ea3o Ch\u1eafc Ch\u1eafn - Tu\u1ea5n T\u00fa Store 68", "trung_nien_nu_49.jpg": "\u00c1o trung ni\u00ean n\u1eef, \u00c1o b\u00e0 ngo\u1ea1i b\u00e0 n\u1ed9i, \u00c1o s\u01a1 mi trung ni\u00ean th\u00eau h\u1ecda ti\u1ebft n\u00fat c\u00e0i sang tr\u1ecdng bigsize t\u1edbi 80kg", "trung_nien_nu_50.jpg": "Qu\u1ea7n \u1ed0ng R\u1ed9ng N\u1eef D\u1ea1ng V\u00e1y Ch\u1ea5t Li\u1ec7u \u0110\u0169i Cao C\u1ea5p M\u00e1t M\u1ebb D\u00e0nh Cho T\u1ea5t C\u1ea3 Ch\u1ecb Em - Tu\u1ea5n T\u00fa Store 68", "trung_nien_nu_51.jpg": "Qu\u1ea7n \u1ed0ng R\u1ed9ng D\u1ea1ng V\u00e1y Ch\u1ea5t Li\u1ec7u L\u1ee5a H\u00e0n Ch\u00e2u M\u1ec1m M\u01b0\u1ee3t Kh\u00f4ng Nh\u0103n Kh\u00f4ng X\u00f9 - Tu\u1ea5n T\u00fa Store 68", "trung_nien_nu_52.jpg": "Bo\u0323\u0302 \u0110o\u0302\u0300 Trung Nie\u0302n Ph\u1ed1i \u00c1o \u0110\u0169i Th\u00eau Hoa V\u1edbi Qu\u1ea7n \u0110\u0169i \u0110en C\u1ef1c \u0110\u1eb9p Ph\u00f9 H\u1ee3p V\u1edbi Ph\u1ee5 N\u1eef T\u1eeb 55-70 Tu\u1ed5i - Tu\u1ea5n T\u00fa Store 68", "trung_nien_nu_53.jpg": "B\u1ed9 \u0110\u0169i Trung Ni\u00ean Hoa Th\u00eau C\u1ef1c \u0110\u1eb9p C\u1ef1c Sang Tr\u1ecdng D\u00e0nh Cho Ph\u1ee5 N\u1eef Vi\u1ec7t Nam 2023 - Laddy Store", "trung_nien_nu_54.jpg": "\u0110\u1ed3 B\u1ed9 N\u1eef Trung Ni\u00ean Sang Tr\u1ecdng B\u1ed9 Ph\u1ed1i \u00c1o Mango C\u1ed9c Tay V\u1edbi Qu\u1ea7n \u0110\u0169i \u0110en Cao C\u1ea5p 2023 - Tu\u1ea5n T\u00fa Store 68", "trung_nien_nu_55.jpg": "\u00c1o Trung Ni\u00ean N\u1eef C\u1ed9c Tay Ch\u1ea5t Li\u1ec7u L\u1ee5a Mango M\u1ec1m M\u1ecbn Tho\u00e1ng M\u00e1t Ki\u1ec3u D\u00e1ng Sang Tr\u1ecdng D\u00e0nh Cho Qu\u00fd B\u00e0 2023 - Tu\u1ea5n T\u00fa Store 68", "trung_nien_nu_56.jpg": "\u0110\u1ea7m trung ni\u00ean cao c\u1ea5p \u0110\u0169i Vi\u1ec7t, thi\u1ebft k\u1ebf c\u1ed5 V tay l\u1ee1, th\u1eddi trang thanh l\u1ecbch Dv190", "trung_nien_nu_57.jpg": "\u0110\u1ea7m su\u00f4ng trung ni\u00ean cao c\u1ea5p d\u00e1ng d\u00e0i c\u1ed5 V \u0111\u00f3ng c\u00fac, V\u00e1y su\u00f4ng n\u1eef tay l\u1ee1 ch\u1ea5t li\u1ec7u linen m\u1ec1m", "trung_nien_nu_58.jpg": "S\u00e9t \u0110\u1ed3 N\u1eef Ch\u1ea5t Li\u1ec7u \u0110\u0169i Si\u00eau M\u1ecbn M\u00e1t D\u00e0nh Cho Ph\u1ee5 N\u1eef Trung Tu\u1ed5i v\u00e0 Cao Tu\u1ed5i 2022 - Tu\u1ea5n T\u00fa Store", "trung_nien_nu_59.jpg": "\u00c1o trung ni\u00ean n\u1eef ch\u1ea5t li\u1ec7u Linen tay ng\u1eafn th\u00eau hoa Haint Boutique ALE21", "trung_nien_nu_60.jpg": "Th\u1eddi Trang Trung Ni\u00ean - B\u1ed9 L\u1ee5a H\u00e0n Ch\u00e2u D\u00e0nh Cho C\u00e1c B\u00e0 C\u00e1c M\u1eb9 2022 - Tu\u1ea5n T\u00fa Store", "trung_nien_nu_61.jpg": "\u0110\u1ea7m \u0110\u1eb9p -V\u00e1y Trung Ni\u00ean, Thi\u1ebft K\u1ebf H\u1ecda Ti\u1ebft Sang Tr\u1ecdng Th\u1eddi Trang D\u1ef1 Ti\u1ec7c \u0110\u0169i Vi\u1ec7t Da70", "trung_nien_nu_62.jpg": "[M\u1eabu M\u1edbi] \u0110\u1ed3 B\u1ed9 N\u1eef Trung Ni\u00ean - C\u1ed9c Tay - Phom R\u1ed9ng - Ch\u1ea5t Li\u1ec7u L\u1ee5a Satin -  M\u1ec1m M\u1ea1i - M\u00e1t M\u1ebb - Tu\u1ea5n T\u00fa Store 68", "trung_nien_nu_63.jpg": "[B\u1ed9 L\u1eedng] - B\u1ed9 Lanh cao c\u1ea5p ( \u0111\u00e3 qua x\u1eed l\u00fd co ) - \u0111\u1ee7 size t\u1eeb 47 - 70kg -  d\u00e0nh cho qu\u00fd b\u00e0 2022 - Laddy Store", "trung_nien_nu_64.jpg": "\u00c1o trung ni\u00ean n\u1eef c\u1ed5 tim phong c\u00e1ch sang tr\u1ecdng ATN08", "trung_nien_nu_65.jpg": "\u00c1o trung ni\u00ean n\u1eef ch\u1ea5t li\u1ec7u thun in h\u1ecda ti\u1ebft", "trung_nien_nu_66.jpg": "(H\u00c0NG S\u1eb4N KHO) \u00c1o len trung ni\u00ean c\u1ed5 cao ph\u1ed1i h\u1ecda ti\u1ebft hoa sen_\u00e1o \u1ea5m thu \u0111\u00f4ng cho b\u00e0 cho m\u1eb9", "trung_nien_nu_67.jpg": "\u0110\u1ed3 b\u1ed9 n\u1eef - ch\u1ea5t li\u1ec7u Nhung tuy\u1ebft cao c\u1ea5p (N3)", "trung_nien_nu_68.jpg": "Qu\u1ea7n \u00c1o Trung Nie\u0302n - B\u1ed9 \u0110\u0169i Tay L\u1ee1 Cao C\u1ea5p \u1ed0ng R\u1ed9ng - \u0110\u1ee7 size cho m\u1ecdi ng\u01b0\u1eddi t\u1eeb 45kg - 68kg - Tu\u1ea5n T\u00fa Store", "trung_nien_nu_69.jpg": "\u00e1o s\u01a1 mi l\u1ee5a Qu\u1ea3ng Ch\u00e2u cao c\u1ea5p cho ng\u01b0\u1eddi trung ni\u00ean _\u00e1o s\u01a1 mi ki\u1ec3u trung ni\u00ean n\u1eef_ \u00e1o s\u01a1 mi l\u1ee5a tay ph\u1ed1i h\u1ecda ti\u1ebft", "trung_nien_nu_70.jpg": "\u00e1o trung ni\u00ean n\u1eef in hoa_\u00e1o l\u1ee5a trung ni\u00ean n\u1eef nh\u1eb9 tho\u00e1ng m\u00e1t", "trung_nien_nu_71.jpg": "\u00c1O S\u01a0 MI TRUNG NI\u00caN", "trung_nien_nu_72.jpg": "\u00e1o s\u01a1 mi trung ni\u00ean \u00e1o v\u1ea3i \u0111\u0169i tay l\u1ee1 d\u00e1ng su\u00f4ng sm38", "trung_nien_nu_73.jpg": "\u0110\u1ea7m trung ni\u00ean bigsize (50kg-90kg) - \u0110\u1ea7m su\u00f4ng in hoa 3D c\u1ef1c \u0111\u1eb9p", "trung_nien_nu_74.jpg": "\u0110\u1ea7m trung ni\u00ean bigsize - \u0110\u1ea7m x\u00f2e A voan hoa tay ren TIFALU900", "trung_nien_nu_75.jpg": "B\u1ed9 tole nhung trung ni\u00ean 50-80kg", "trung_nien_nu_76.jpg": "\u0110\u1ed3 b\u1ed9 trung ni\u00ean \u0111\u1eb9p 2021 -  B\u1ed9 \u0111\u0169i cao c\u1ea5p - ch\u1ea5t v\u1ea3i lo\u1ea1i 1 - Kh\u00f4ng nh\u0103n kh\u00f4ng x\u00f9 khi gi\u1eb7t - (72) - Laddy_store", "trung_nien_nu_77.jpg": "B\u1ed9 Trung Ni\u00ean Tay L\u1ee1 - B\u1ed9 Ph\u1ed1i \u00c1o L\u1ee5a h\u00e0n Ch\u00e2u, Qu\u1ea7n \u0110\u0169i cao c\u1ea5p - Kh\u00f4ng nh\u0103n kh\u00f4ng x\u00f9 khi gi\u1eb7t - Tu\u1ea5n T\u00fa Store 68", "trung_nien_nu_78.jpg": "\u0110\u1ed3 B\u1ed9 Trung Ni\u00ean Tay L\u1ee1 - L\u1ee5a H\u00e0n Ch\u00e2u, Qu\u1ea7n \u0110\u0169i Cao C\u1ea5p, Si\u00eau M\u1ec1m, Si\u00eau M\u00e1t D\u00e0nh cho Qu\u00fd B\u00e0 Trung Tu\u1ed5i - Tu\u1ea5n T\u00fa Store 68", "trung_nien_nu_79.jpg": "\u0110o\u0302\u0300 Bo\u0323\u0302 Nu\u031b\u0303 Trung Nie\u0302n Cao C\u1ea5p Tay L\u1ee1-  \u0110\u0169i Cao C\u1ea5p - V\u1ea3i lo\u1ea1i 1 - Kh\u00f4ng nh\u0103n kh\u00f4ng x\u00f9 khi gi\u1eb7t - Tu\u1ea5n T\u00fa Store 68", "trung_nien_nu_80.jpg": "B\u1ed9 s\u01a1 mi n\u1eef trung ni\u00ean \u00c1o c\u00f3 c\u1ed5 v\u00e0 khuy c\u00e0i ch\u1ea5t li\u1ec7u l\u1ee5a h\u00e0n ch\u00e2u cao c\u1ea5p m\u1ec1m m\u00e1t kh\u00f4ng nh\u0103n x\u00f9 khi gi\u1eb7t - Tu\u1ea5n T\u00fa Store 68", "trung_nien_nu_81.jpg": "\u00c1o Cho M\u1eb9 Ch\u1ea5t Li\u1ec7u Satin Cao C\u1ea5p M\u1ec1m M\u01b0\u1ee3t T\u00f4n D\u00e1ng Sang Tr\u1ecdng Ph\u00f9 H\u1ee3p V\u1edbi B\u00e0 V\u00e0 M\u1eb9 - Tu\u1ea5n T\u00fa Store 68", "trung_nien_nu_82.jpg": "\u00c1o Trung Ni\u00ean N\u1eef Tay L\u1ee1 Ch\u1ea5t Li\u1ec7u L\u1ee5a H\u00e0n Ch\u00e2u Cao C\u1ea5p H\u1ecda Ti\u1ebft Tinh X\u1ea3o Kh\u00f4ng Nh\u0103n X\u00f9 Khi Gi\u1eb7t - Tu\u1ea5n T\u00fa Store 68", "trung_nien_nu_83.jpg": "\u00c1o Voan 2 L\u1edbp S\u00e0nh \u0110i\u1ec7u D\u00e0nh Cho Ph\u1ee5 N\u1eef Trung Ni\u00ean Hi\u1ec7n \u0110\u1ea1i - Tu\u1ea5n T\u00fa Store 68", "trung_nien_nu_84.jpg": "B\u1ed9 Ph\u1ed1i \u00c1o Mango Cao C\u1ea5p V\u00e0 Qu\u1ea7n \u0110\u0169i Cho B\u00e0 V\u00e0 M\u1eb9 C\u1ef1c K\u1ef3 Sang Tr\u1ecdng - Tu\u1ea5n T\u00fa Store 68", "trung_nien_nu_85.jpg": "Qu\u1ea7n \u1ed0ng R\u1ed9ng D\u1ea1ng V\u00e1y Cho N\u1eef Ch\u1ea5t Li\u1ec7u Lanh L\u1ee5a Cao C\u1ea5p M\u1ec1m M\u1ecbn V\u00e0 C\u1ef1c M\u00e1t - Tu\u1ea5n T\u00fa Store 68", "trung_nien_nu_86.jpg": "\u0110\u1ea7m x\u00f2e thi\u1ebft k\u1ebf trung ni\u00ean cao c\u1ea5p sang tr\u1ecdng C\u1ed5 tr\u00f2n kho\u00e9t V tay ng\u1eafn m\u00e0u \u0110en hoa kem TTV STORE TTV1413", "trung_nien_nu_87.jpg": "\u0110\u1ea7m x\u00f2e thi\u1ebft k\u1ebf trung ni\u00ean cao c\u1ea5p C\u1ed5 V k\u1ebft n\u00fat tay l\u1ee1 m\u00e0u N\u00e2u cafe TTV STORE TTV1392", "trung_nien_nu_88.jpg": "\u0110\u1ea7m su\u00f4ng thi\u1ebft k\u1ebf trung ni\u00ean cao c\u1ea5p sang tr\u1ecdng C\u1ed5 vu\u00f4ng tay l\u1ee1 m\u00e0u \u0110en hoa t\u00edm TTV STORE TTV1377", "trung_nien_nu_89.jpg": "\u0110\u1ea7m su\u00f4ng thi\u1ebft k\u1ebf trung ni\u00ean qu\u00fd ph\u00e1i cao c\u1ea5p C\u1ed5 tr\u00f2n \u0111\u00ednh ng\u1ecdc tay l\u1ee1 k\u1ebft hoa m\u00e0u H\u1ed3ng ru\u1ed1c TTV STORE TTV1368", "trung_nien_nu_90.jpg": "Th\u1eddi Trang N\u1eef Trung Ni\u00ean B\u1ed9 L\u1ee5a H\u00e0n Ch\u00e2u Cao C\u1ea5p Kh\u00f4ng Nh\u0103n X\u00f9 Khi Gi\u1eb7t Ph\u00f9 H\u1ee3p V\u1edbi M\u1eb9 V\u00e0 B\u00e0 2023 - Tu\u1ea5n T\u00fa Store 68", "trung_nien_nu_91.jpg": "\u0110\u1ea7m xo\u00e8 thi\u1ebft k\u1ebf trung ni\u00ean cao c\u1ea5p sang tr\u1ecdng C\u1ed5 tr\u00f2n k\u1ebft hoa tay l\u1ee1 m\u00e0u \u0110en TTV STORE TTV1253", "trung_nien_nu_92.jpg": "\u0110\u1ea7m x\u00f2e thi\u1ebft k\u1ebf trung ni\u00ean cao c\u1ea5p sang tr\u1ecdng C\u1ed5 tim c\u1ed9t n\u01a1 tay d\u00e0i m\u00e0u Xanh t\u00edm TTV STORE TTV1126", "trung_nien_nu_93.jpg": "\u0110\u1ea7m x\u00f2e thi\u1ebft k\u1ebf trung ni\u00ean sang tr\u1ecdng C\u1ed5 vu\u00f4ng k\u1ebft n\u00fat tay bo m\u00e0u \u0110en kem TTV STORE TTV1268", "trung_nien_nu_94.jpg": "\u0110\u1ea7m xo\u00e8 trung ni\u00ean TTV Store TTV1158 c\u1ed5 tr\u00f2n tay ng\u1eafn thi\u1ebft k\u1ebf Xanh c\u1ed5 v\u1ecbt di ch\u01a1i \u0111i ti\u1ec7c sang tr\u1ecdng", "trung_nien_nu_95.jpg": "\u0110\u1ea7m xo\u00e8 th\u1eddi trang trung ni\u00ean TTV Store C\u1ed5 vu\u00f4ng n\u01a1 tay loe thi\u1ebft k\u1ebf Xanh d\u01b0\u01a1ng TTV1183 thanh l\u1ecbch", "trung_nien_nu_96.jpg": "\u00c1o ki\u1ec3u trung ni\u00ean n\u1eef \u0111\u1eb9p, S\u01a1 mi tay ph\u1ed1i h\u1ecda ti\u1ebft voan hoa c\u1ed5 b\u1ebb, Ch\u1ea5t li\u1ec7u thun cotton m\u1ec1m m\u00e1t, Qu\u00e0 xinh t\u1eb7ng m\u1eb9 y\u00eau", "trung_nien_nu_97.jpg": "\u00c1o cardigan len, \u00c1o kho\u00e1c len trung ni\u00ean d\u1ec7t kim th\u00eau hoa c\u00e0i c\u00fac, Full size- M\u00f3n qu\u00e0 t\u1eb7ng b\u00e0 t\u1eb7ng m\u1eb9 KLGN06", "trung_nien_nu_98.jpg": "\u0110\u1ed3 B\u1ed9 \u1ed0ng R\u1ed9ng Cho M\u1eb9 Ch\u1ea5t Li\u1ec7u L\u1ee5a H\u00e0n Ch\u00e2u Si\u00eau M\u1ec1m M\u1ecbn V\u00e0 T\u00f4n D\u00e1ng - Tu\u1ea5n T\u00fa Store", "trung_nien_nu_99.jpg": "\u00c1o Ki\u1ec3u N\u1eef Cho M\u1eb9 Ch\u1ea5t Li\u1ec7u L\u1ee5a H\u00e0n Ch\u00e2u Phom D\u00e1ng C\u1ef1c Chu\u1ea9n \u0110\u1ee7 Size t\u1eeb 45kg t\u1edbi 68kg - Tu\u1ea5n T\u00fa Store", "trung_nien_nu_100.jpg": "\u0110\u1ed3 Cho M\u1eb9 Trung Ni\u00ean B\u1ed9 \u0110\u1ed3 Ph\u1ed1i \u00c1o L\u1ee5a H\u00e0n Ch\u00e2u v\u00e0 Qu\u1ea7n \u0110\u0169i \u0110en Cao C\u1ea5p 2022 - Tu\u1ea5n T\u00fa Store", "trung_nien_nu_101.jpg": "B\u1ed9 \u0110\u1ed3 Trung Ni\u00ean Ph\u1ed1i \u00c1o L\u1ee5a Satin v\u00e0 Qu\u1ea7n \u0110\u0169i L\u1ee5a Cao C\u1ea5p Cho M\u1eb9 Ph\u00f9 H\u1ee3p M\u1eb7c \u0110i Ra Ngo\u00e0i c\u0169ng nh\u01b0 \u1edf Nh\u00e0 - Tu\u1ea5n T\u00fa Store", "trung_nien_nu_102.jpg": "\u0110\u1ea7m \u0111i ti\u1ec7c sang tr\u1ecdng form xo\u00e8 c\u1ed5 tr\u00f2n tay ng\u1eafn peplum cam s\u1eefa TTV1047", "trung_nien_nu_103.jpg": "\u00c1o len trung ni\u00ean n\u1eef c\u1ed5 cao tay d\u00e0i ph\u1ed1i hoa ALN06 m\u00f3n qu\u00e0 t\u1eb7ng cho b\u00e0 cho m\u1eb9", "trung_nien_nu_104.jpg": "\u00c1o trung ni\u00ean ARCTIC HUNTER thi\u1ebft k\u1ebf tay b\u00fap sen v\u1ea3i voan \u0111\u1eb9p A92", "trung_nien_nu_105.jpg": "\u00c1o Thun Hoa Decembery D\u00e1ng Ng\u1eafn", "trung_nien_nu_106.jpg": "(M\u1eabu M\u1edbi) \u00c1o Ki\u1ec3u Trung Ni\u00ean 2022  - L\u1ee5a H\u00e0n Ch\u00e2u Cao C\u1ea5p - M\u1ec1m M\u1ea1i - Tr\u1ebb Trung Cho C\u00e1c Qu\u00fd B\u00e0 - Tu\u1ea5n T\u00fa Store", "trung_nien_nu_107.jpg": "\u0110\u1ea7m thi\u1ebft k\u1ebf d\u00e1ng su\u00f4ng TFL803 \u2013 V\u00e1y \u0111\u1ea7m trung ni\u00ean bigsize TIFALU", "trung_nien_nu_108.jpg": "\u00c1O LEN TRUNG NI\u00caN PH\u1ed0I HOA SANG TR\u1eccNG_ \u00c1O \u1ea4M M\u00d9A \u0110\u00d4NG CHO B\u00c0 CHO M\u1eb8(H\u00c0NG S\u1eb4N KHO)", "trung_nien_nu_109.jpg": "B\u1ed9 \u0111\u1ed3 ch\u1ea5t \u0111\u0169i trung ni\u00ean", "trung_nien_nu_110.jpg": "B\u1ed9 nhung - ki\u1ec3u d\u00e1ng sang tr\u1ecdng, qu\u00fd ph\u00e1i (N3)", "trung_nien_nu_111.jpg": "B\u1ed9 nhung - ki\u1ec3u d\u00e1ng sang tr\u1ecdng, qu\u00fd ph\u00e1i (N3)", "trung_nien_nu_112.jpg": "B\u1ed9 nhung - ki\u1ec3u d\u00e1ng sang tr\u1ecdng, qu\u00fd ph\u00e1i (N3)", "trung_nien_nu_113.jpg": "\u0110\u1ed3 b\u1ed9 trung ni\u00ean m\u1eb7c nh\u00e0 cho b\u00e0 cho m\u1eb9", "trung_nien_nu_114.jpg": "B\u1ed8 M\u1eb6C NH\u00c0 TRUNG NI\u00caN- B\u1ed8 \u0110\u1ed2 TRUNG NI\u00caN CHO B\u00c0 CHO M\u1eb8", "trung_nien_nu_115.jpg": "B\u1ed9 \u0111\u1ed3 trung ni\u00ean pyjama h\u1ecda ti\u1ebft tay d\u00e0i dn21072802", "trung_nien_nu_116.jpg": "\u0110\u1ea7m trung ni\u00ean h\u1ecda ti\u1ebft dn21072801", "trung_nien_nu_117.jpg": "Qu\u1ea7n n\u1eef trung ni\u00ean c\u1ea1p chun c\u1ef1c \u0111\u1eb9p", "trung_nien_nu_118.jpg": "\u0110\u1ed3 b\u1ed9 trung ni\u00ean cao c\u1ea5p - l\u1ee5a h\u00e0n ch\u00e2u si\u00eau m\u1ec1m, si\u00eau m\u00e1t - Sang Tr\u1ecdng v\u00e0 Qu\u00fd Ph\u00e1i d\u00e1nh cho c\u00e1c Qu\u00fd B\u00e0 - Tu\u1ea5n T\u00fa Store 68", "trung_nien_nu_119.jpg": "\u00c1o Women's Dress  PONY - 4950001/02LWQ1", "trung_nien_nu_120.jpg": "\u0110\u1ed3 b\u1ed9 trung ni\u00ean n\u1eef form r\u1ed9ng, Ch\u1ea5t li\u1ec7u L\u1ee5a B\u00f2 m\u1ec1m m\u1ecbn, nh\u1eb9, m\u1eb7c m\u00e1t, B\u1ed3 b\u1ed9 n\u1eef cao c\u1ea5p t\u1eb7ng b\u00e0 t\u1eb7ng m\u1eb9 sang tr\u1ecdng", "trung_nien_nu_121.jpg": "H\u1ed9p 40 Mi\u1ebfng D\u00e1n Th\u1ea5m M\u1ed3 H\u00f4i N\u00e1ch P98 - H\u1ea1n Ch\u1ebf M\u1ed3 H\u00f4i N\u00e1ch [ C\u00d3 CHE T\u00caN KHI GIAO H\u00c0NG", "trung_nien_nu_122.jpg": "B\u1ed9 l\u1ee5a mango cao c\u1ea5p 50-75kg, \u0110\u1ed3 b\u1ed9 m\u1eb7c nh\u00e0", "trung_nien_nu_123.jpg": "B\u1ed9 Lanh Cao C\u1ea5p \u00c1o S\u00e1t N\u00e1ch Qu\u1ea7n \u0110\u00f9i Cho N\u1eef - Tu\u1ea5n T\u00fa Store 68", "trung_nien_nu_124.jpg": "\u00c1o Ki\u1ec3u Tay L\u1ee1 Ch\u1ea5t Li\u1ec7u L\u1ee5a Mango Cao C\u1ea5p M\u1ec1m M\u1ecbn Sang Tr\u1ecdng Cho B\u00e0 V\u00e0 M\u1eb9 - Tu\u1ea5n T\u00fa Store 68", "trung_nien_nu_125.jpg": "\u0110\u1ea7m Form A thi\u1ebft k\u1ebf d\u00e1ng d\u00e0i C\u1ed5 tr\u00f2n tay l\u1edf ph\u1ed1i ren m\u00e0u T\u00edm c\u1ea9m TTV STORE TTV1389", "trung_nien_nu_126.jpg": "\u0110\u1ed3 B\u1ed9 L\u1ee5a Satin N\u1eef Trung Ni\u00ean Cao C\u1ea5p Sang Tr\u1ecdng Cho M\u1eb9 Cho B\u00e0 2023 - Tu\u1ea5n T\u00fa Store 68", "trung_nien_nu_127.jpg": "B\u1ed9 L\u1ee5a Cao C\u1ea5p D\u00e0nh Cho Ph\u1ee5 N\u1eef Tu\u1ed5i Trung Ni\u00ean 2023 - Tu\u1ea5n T\u00fa Store 68", "trung_nien_nu_128.jpg": "Qu\u1ea7n \u1ed0ng R\u1ed9ng N\u1eef Ch\u1ea5t Li\u1ec7u \u0110\u0169i Hoa Th\u00eau Tinh X\u1ea3o Tr\u1ebb Trung 2023 - Tu\u1ea5n T\u00fa Store 68", "trung_nien_nu_129.jpg": "\u0110a\u0302\u0300m Trung Nie\u0302n Sang Tro\u0323ng Ch\u1ea5t Li\u1ec7u L\u1ee5a Mango Cao C\u1ea5p D\u00e0nh Cho M\u1eb9 T\u1eeb 55-70 Tu\u1ed5i - Tu\u1ea5n T\u00fa Store 68", "trung_nien_nu_130.jpg": "\u0110\u1ea7m x\u00f2e trung ni\u00ean TTV1207 TTV Store thi\u1ebft k\u1ebf C\u1ed5 tim x\u1ebfp li tay ng\u1eafn m\u00e0u Xanh c\u1ed5 v\u1ecbt th\u1eddi trang tr\u1ebb trung", "trung_nien_nu_131.jpg": "\u0110\u1ea7m xo\u00e8 trung ni\u00ean TTV Store TTV1183 C\u1ed5 vu\u00f4ng n\u01a1 tay loe thi\u1ebft k\u1ebf m\u00e0u \u0110en sang tr\u1ecdng", "trung_nien_nu_132.jpg": "\u0110\u1ea7m form A n\u1eef trung ni\u00ean thi\u1ebft k\u1ebf C\u1ed5 vu\u00f4ng tay ng\u1eafn gam m\u00e0u T\u00edm hu\u1ebf TTV1153", "trung_nien_nu_133.jpg": "[BST M\u1edbi] B\u1ed9 m\u1eb7c nh\u00e0 trung ni\u00ean cho m\u1eb9, cho b\u00e0 Vicci DTL01 thi\u1ebft k\u1ebf tay l\u1ee1 qu\u1ea7n d\u00e0i, ch\u1ea5t li\u1ec7u v\u1ea3i \u0111\u0169i chun m\u1ec1m m\u1ecbn ph\u1ed1i h\u1ecda ti\u1ebft th\u00eau hoa", "trung_nien_nu_134.jpg": "\u00c1o Ki\u1ec3u N\u1eef Cho M\u1eb9 Ch\u1ea5t Li\u1ec7u L\u1ee5a Satin Si\u00eau M\u1ec1m M\u01b0\u1ee3t Si\u00eau T\u00f4n D\u00e1ng 2022 - Tu\u1ea5n T\u00fa Store", "trung_nien_nu_135.jpg": "S\u00e9t b\u1ed9 l\u1eedng bigsize n\u1eef CAO C\u1ea4P- \u0111\u1ed3 b\u1ed9 d\u1ea1o ph\u1ed1 m\u1eb7c nh\u00e0 trung ni\u00ean c\u1ed5 b\u1ebb ph\u1ed1i s\u1ecdc", "trung_nien_nu_136.jpg": "B\u1ed9 Tole Nhung D\u00e0i trung ni\u00ean  tay c\u1ecdc 40-75kg phom chu\u1ea9n \u0111\u1eb9p ,\u0111\u01b0\u1eddng may ch\u1eafc ch\u1eafn", "trung_nien_nu_137.jpg": "B\u1ed8 M\u1eb6C NH\u00c0 TRUNG NI\u00caN- B\u1ed8 \u0110\u1ed2 TRUNG NI\u00caN CHO B\u00c0 CHO M\u1eb8", "trung_nien_nu_138.jpg": "\u0110\u1ed3 b\u1ed9 trung ni\u00ean cho m\u1eb9 . th\u1eddi trang trung ni\u00ean - \u0111\u1ed3 b\u1ed9 cao c\u1ea5p", "trung_nien_nu_139.jpg": " \u0110\u1ed3 b\u1ed9 trung ni\u00ean"}